config_kit/__init__.py
config_kit/bin.py
config_kit/core.py
config_kit/util.py
config_kit/version.json
config_kit-1.0.0.dist-info/METADATA
config_kit-1.0.0.dist-info/WHEEL
config_kit-1.0.0.dist-info/entry_points.txt
config_kit-1.0.0.dist-info/top_level.txt
config_kit-1.0.0.dist-info/RECORD
